hyperv/__init__.py
hyperv/hyperv.py
hyperv/net.py
hyper_v-0.0.3.dist-info/METADATA
hyper_v-0.0.3.dist-info/WHEEL
hyper_v-0.0.3.dist-info/top_level.txt
hyper_v-0.0.3.dist-info/RECORD
