Metadata-Version: 2.1
Name: hyper-v
Version: 0.0.3
Summary: Удаленное управление Hyper-V через winrm
Home-page: https://github.com/viktor-gorinskiy/hyper-v
Author: Viktor Gorinskiy
Author-email: viktor@gorinskiy.ru
License: UNKNOWN
Platform: UNKNOWN
Classifier: Programming Language :: Python :: 3.8
Classifier: License :: OSI Approved :: MIT License
Classifier: Operating System :: OS Independent
Requires-Python: >=3.6
Requires-Dist: pywinrm (==0.4.3)
